{"native_th": "\u0e20\u0e32\u0e29\u0e32\u0e44\u0e17\u0e22", "PercentDodgeMod": "% \u03b1\u03c0\u03bf\u03c6\u03c5\u03b3\u03ae\u03c2", "Continue": "\u03a3\u03c5\u03bd\u03ad\u03c7\u03b5\u03b9\u03b1", "Map11": "\u03a6\u03b1\u03c1\u03ac\u03b3\u03b3\u03b9 \u03c4\u03c9\u03bd \u0395\u03c0\u03b9\u03ba\u03b1\u03bb\u03b5\u03c3\u03c4\u03ce\u03bd", "native_it": "Italiano", "FlatMPRegenMod": "\u0391\u03bd\u03b1\u03c0\u03bb\u03ae\u03c1\u03c9\u03c3\u03b7 \u039c\u03ac\u03bd\u03b1 / 5", "mobileNews": "\u039d\u03ad\u03b1", "mobilePleaseWait": "\u03a0\u03b5\u03c1\u03b9\u03bc\u03ad\u03bd\u03b5\u03c4\u03b5...", "Aura": "\u0391\u03cd\u03c1\u03b1", "Cost_": "\u039a\u03cc\u03c3\u03c4\u03bf\u03c2:", "PercentEXPBonus": "% \u039c\u03c0\u03cc\u03bd\u03bf\u03c5\u03c2 \u03b5\u03bc\u03c0\u03b5\u03b9\u03c1\u03af\u03b1\u03c2", "CooldownReduction": "\u039c\u03b5\u03af\u03c9\u03c3\u03b7 \u03a7\u03c1\u03cc\u03bd\u03bf\u03c5 \u0395\u03c0\u03b1\u03bd\u03b1\u03c6\u03cc\u03c1\u03c4\u03b9\u03c3\u03b7\u03c2", "rPercentMagicPenetrationMod": "\u0394\u03b9\u03b5\u03af\u03c3\u03b4\u03c5\u03c3\u03b7 \u03bc\u03b1\u03b3\u03b5\u03af\u03b1\u03c2 %", "ButtonBuy": "\u0391\u0393\u039f\u03a1\u0391", "colloq_Movement": ";movespeed;ms", "physicalDamageDealtToChampions": "\u03a3\u03c9\u03bc\u03b1\u03c4\u03b9\u03ba\u03ae \u03b6\u03b7\u03bc\u03b9\u03ac \u03c3\u03b5 \u03ae\u03c1\u03c9\u03b5\u03c2", "wardsPlaced": "\u039c\u03ac\u03c4\u03b9\u03b1 \u03c0\u03bf\u03c5 \u03c4\u03bf\u03c0\u03bf\u03b8\u03b5\u03c4\u03ae\u03b8\u03b7\u03ba\u03b1\u03bd", "Language": "\u0393\u03bb\u03ce\u03c3\u03c3\u03b1", "rFlatMPModPerLevel": "\u039c\u03ac\u03bd\u03b1 \u03c3\u03c4\u03bf \u03b5\u03c0. 18", "Attack": "\u0395\u03c0\u03af\u03b8\u03b5\u03c3\u03b7", "Mana": "\u039c\u03ac\u03bd\u03b1", "colloq_NonbootsMovement": ";", "rPercentCooldownModPerLevel": "% \u03a7\u03c1\u03cc\u03bd\u03bf\u03c2 \u0395\u03c0\u03b1\u03bd. \u03c3\u03c4\u03bf \u03b5\u03c0. 18", "colloq_ManaRegen": ";mpregen;mp5;\u03b1\u03bd\u03b1\u03c0\u03bb. \u039c\u03ac\u03bd\u03b1;\u03bc\u03ac\u03bd\u03b1 \u03b1\u03bd\u03ac 5", "Lore": "\u039c\u03c5\u03b8\u03bf\u03bb\u03bf\u03b3\u03af\u03b1", "native_fr": "fran\u00e7ais", "colloq_Active": ";", "rFlatHPModPerLevel": "\u0396\u03c9\u03ae \u03c3\u03c4\u03bf \u03b5\u03c0. 18", "damageDealt": "\u0396\u03b7\u03bc\u03b9\u03ac \u03c0\u03bf\u03c5 \u03ad\u03c7\u03b5\u03b9 \u03c0\u03c1\u03bf\u03ba\u03bb\u03b7\u03b8\u03b5\u03af", "modeFirstblood": "FRONTEND_firstblood_game_mode_name", "Boots": "\u039c\u03c0\u03cc\u03c4\u03b5\u03c2", "native_nl": "Nederlands", "recommended_essential": "\u0391\u03c0\u03b1\u03c1\u03b1\u03af\u03c4\u03b7\u03c4\u03b1 \u03b1\u03bd\u03c4\u03b9\u03ba\u03b5\u03af\u03bc\u03b5\u03bd\u03b1", "colloq_Consumable": ";", "Rank_": "\u0392\u03b1\u03b8\u03bc\u03af\u03b4\u03b1:", "modeClassic": "\u039a\u03bb\u03b1\u03c3\u03b9\u03ba\u03cc", "FlatHPRegenMod": "\u0391\u03bd\u03b1\u03c0\u03bb\u03ae\u03c1\u03c9\u03c3\u03b7 \u0396\u03c9\u03ae\u03c2 / 5", "native_de": "Deutsch", "totalMinionsKilled": "\u03a5\u03c0\u03b7\u03c1\u03ad\u03c4\u03b5\u03c2 \u03c0\u03bf\u03c5 \u03c3\u03ba\u03bf\u03c4\u03ce\u03b8\u03b7\u03ba\u03b1\u03bd", "Tank": "\u03a4\u03b1\u03bd\u03ba", "PercentBlockMod": "% \u03bc\u03c0\u03bb\u03bf\u03ba\u03b1\u03c1\u03af\u03c3\u03bc\u03b1\u03c4\u03bf\u03c2", "native_hu": "magyar", "native_el": "\u03b5\u03bb\u03bb\u03b7\u03bd\u03b9\u03ba\u03ac", "rFlatCritDamageModPerLevel": "\u0396\u03b7\u03bc\u03b9\u03ac \u039a\u03b1\u03af\u03c1\u03b9\u03bf\u03c5 \u03a7\u03c4. \u03c3\u03c4\u03bf \u03b5\u03c0. 18", "firstBloodKill": "\u03a0\u03c1\u03ce\u03c4\u03bf \u03b1\u03af\u03bc\u03b1", "Mage": "\u039c\u03ac\u03b3\u03bf\u03c2", "magicDamageDealt": "\u039c\u03b1\u03b3\u03b9\u03ba\u03ae \u03b6\u03b7\u03bc\u03b9\u03ac \u03c3\u03b5 \u03b5\u03c7\u03b8\u03c1\u03bf\u03cd\u03c2", "modeOdin": "\u0394\u03b5\u03bd \u03b5\u03af\u03bd\u03b1\u03b9 \u03b7 \u039a\u03c5\u03c1\u03b9\u03b1\u03c1\u03c7\u03af\u03b1", "rPercentMagicPenetrationModPerLevel": "\u0394\u03b9\u03b5\u03af\u03c3\u03b4\u03c5\u03c3\u03b7 \u03bc\u03b1\u03b3\u03b5\u03af\u03b1\u03c2 % \u03c3\u03c4\u03bf \u03b5\u03c0. 18", "colloq_Slow": ";", "colloq_SpellVamp": ";\u0391\u03c1\u03c0\u03b1\u03b3\u03ae \u0396\u03c9\u03ae\u03c2 \u03bc\u03b5 \u03bc\u03b1\u03b3\u03b5\u03af\u03b1;spellvamp", "Abilities": "\u0399\u03ba\u03b1\u03bd\u03cc\u03c4\u03b7\u03c4\u03b5\u03c2", "native_pl": "j\u0119zyk polski", "rFlatMagicPenetrationModPerLevel": "\u0394\u03b9\u03b5\u03af\u03c3\u03b4\u03c5\u03c3\u03b7 \u039c\u03b1\u03b3\u03b5\u03af\u03b1\u03c2 \u03c3\u03c4\u03bf \u03b5\u03c0. 18", "Marksman": "\u03a3\u03ba\u03bf\u03c0\u03b5\u03c5\u03c4\u03ae\u03c2", "Assassin": "\u0394\u03bf\u03bb\u03bf\u03c6\u03cc\u03bd\u03bf\u03c2", "rPercentTimeDeadMod": "% \u0394\u03b9\u03ac\u03c1\u03ba\u03b5\u03b9\u03b1 \u0398\u03b1\u03bd\u03ac\u03c4\u03bf\u03c5", "rFlatDodgeModPerLevel": "\u0391\u03c0\u03bf\u03c6\u03c5\u03b3\u03ae \u03c3\u03c4\u03bf \u03b5\u03c0. 18", "rPercentArmorPenetrationModPerLevel": "\u0394\u03b9\u03b5\u03af\u03c3\u03b4\u03c5\u03c3\u03b7 \u0398\u03c9\u03c1\u03ac\u03ba\u03b9\u03c3\u03b7\u03c2 % \u03c3\u03c4\u03bf \u03b5\u03c0. 18", "combat": "\u039c\u03ac\u03c7\u03b7", "CD_": "\u03a7\u03c1\u03cc\u03bd\u03bf\u03c2 \u03b5\u03c0\u03b1\u03bd\u03b1\u03c6\u03cc\u03c1\u03c4\u03b9\u03c3\u03b7\u03c2:", "rFlatTimeDeadMod": "\u0394\u03b9\u03ac\u03c1\u03ba\u03b5\u03b9\u03b1 \u0398\u03b1\u03bd\u03ac\u03c4\u03bf\u03c5", "totalDamageTaken": "\u0396\u03b7\u03bc\u03b9\u03ac \u03b1\u03c0\u03cc \u03b5\u03c7\u03b8\u03c1\u03bf\u03cd\u03c2", "Details_": "\u03a3\u03c4\u03bf\u03b9\u03c7\u03b5\u03af\u03b1:", "colloq_AttackSpeed": ";as", "spells_target_2": "\u03a0\u03b5\u03c1\u03b9\u03bf\u03c7\u03ae", "colloq_ArmorPenetration": ";", "trueDamageTaken": "\u03a0\u03c1\u03b1\u03b3\u03bc\u03b1\u03c4\u03b9\u03ba\u03ae \u03b6\u03b7\u03bc\u03b9\u03ac \u03b1\u03c0\u03cc \u03b1\u03bd\u03c4\u03b9\u03c0\u03ac\u03bb\u03bf\u03c5\u03c2", "income": "\u0395\u03b9\u03c3\u03cc\u03b4\u03b7\u03bc\u03b1", "magicDamageDealtToChampions": "\u039c\u03b1\u03b3\u03b9\u03ba\u03ae \u0396\u03b7\u03bc\u03b9\u03ac \u03c3\u03b5 \u0389\u03c1\u03c9\u03b5\u03c2", "modeCof": "FRONTEND_cof_game_mode_name", "MagicPenetration": "\u0394\u03b9\u03b5\u03af\u03c3\u03b4\u03c5\u03c3\u03b7 \u039c\u03b1\u03b3\u03b5\u03af\u03b1\u03c2", "recommended_offensive": "\u0395\u03c0\u03b9\u03b8\u03b5\u03c4\u03b9\u03ba\u03ac \u03b1\u03bd\u03c4\u03b9\u03ba\u03b5\u03af\u03bc\u03b5\u03bd\u03b1", "SpellVamp": "\u039c\u03b1\u03b3\u03b9\u03ba\u03ae \u0391\u03c1\u03c0\u03b1\u03b3\u03ae \u0396\u03c9\u03ae\u03c2", "Tenacity": "\u0395\u03bc\u03bc\u03bf\u03bd\u03ae", "SpellBlock": "\u0391\u03bd\u03c4\u03af\u03c3\u03c4\u03b1\u03c3\u03b7 \u039c\u03b1\u03b3\u03b5\u03af\u03b1\u03c2", "FlatPhysicalDamageMod": "\u03a3\u03c9\u03bc\u03b1\u03c4\u03b9\u03ba\u03ae \u0396\u03b7\u03bc\u03b9\u03ac", "rFlatEnergyModPerLevel": "\u0395\u03bd\u03ad\u03c1\u03b3\u03b5\u03b9\u03b1 \u03c3\u03c4\u03bf \u03b5\u03c0. 18", "colloq_Tenacity": ";", "NonbootsMovement": "\u0386\u03bb\u03bb\u03b1 \u03b1\u03bd\u03c4\u03b9\u03ba\u03b5\u03af\u03bc\u03b5\u03bd\u03b1 \u03ba\u03af\u03bd\u03b7\u03c3\u03b7\u03c2", "totalDamageDealtToChampions": "\u03a3\u03c5\u03bd\u03bf\u03bb\u03b9\u03ba\u03ae \u03b6\u03b7\u03bc\u03b9\u03ac \u03c3\u03b5 \u03ae\u03c1\u03c9\u03b5\u03c2", "rPercentTimeDeadModPerLevel": "% \u0394\u03b9\u03ac\u03c1\u03ba\u03b5\u03b9\u03b1 \u0398\u03b1\u03bd\u03ac\u03c4\u03bf\u03c5 / \u03b5\u03c0.", "Armor": "\u0398\u03c9\u03c1\u03ac\u03ba\u03b9\u03c3\u03b7", "native_tr": "T\u00fcrk\u00e7e", "FlatMPPoolMod": "\u039c\u03ac\u03bd\u03b1", "colloq_Boots": ";", "Map12": "\u039c\u03b1\u03b9\u03bd\u03cc\u03bc\u03b5\u03bd\u03b7 \u0386\u03b2\u03c5\u03c3\u03c3\u03bf\u03c2", "native_ro": "rom\u00e2n\u0103", "spells_target_3": "\u039a\u03ce\u03bd\u03bf\u03c2", "neutralMinionsKilledEnemyJungle": "\u0395\u03ba\u03c4\u03b5\u03bb\u03ad\u03c3\u03b5\u03b9\u03c2 \u03bf\u03c5\u03b4\u03ad\u03c4\u03b5\u03c1\u03c9\u03bd \u03c4\u03b5\u03c1\u03ac\u03c4\u03c9\u03bd \u03c3\u03c4\u03b7 \u03b6\u03bf\u03cd\u03b3\u03ba\u03bb\u03b1 \u03c4\u03bf\u03c5 \u03b1\u03bd\u03c4\u03b9\u03c0\u03ac\u03bb\u03bf\u03c5", "largestCriticalStrike": "\u0399\u03c3\u03c7\u03c5\u03c1\u03cc\u03c4\u03b5\u03c1\u03bf \u03ba\u03b1\u03af\u03c1\u03b9\u03bf \u03c7\u03c4\u03cd\u03c0\u03b7\u03bc\u03b1", "spells_target_0": "\u039c\u03bf\u03bd\u03ac\u03b4\u03b1", "rFlatGoldPer10Mod": "\u03a7\u03c1\u03c5\u03c3\u03cc\u03c2 \u03b1\u03bd\u03ac 10", "FlatCritChanceMod": "\u03a0\u03b9\u03b8\u03b1\u03bd\u03cc\u03c4\u03b7\u03c4\u03b1 \u039a\u03b1\u03af\u03c1\u03b9\u03bf\u03c5 \u03a7\u03c4.", "Map10": "\u0394\u03ac\u03c3\u03bf\u03c2 \u03c4\u03b7\u03c2 \u03a3\u03cd\u03b3\u03c7\u03c5\u03c3\u03b7\u03c2", "categoryMastery": "\u0395\u03be\u03b5\u03b9\u03b4\u03b9\u03ba\u03b5\u03cd\u03c3\u03b5\u03b9\u03c2", "ButtonSell": "\u03a0\u03a9\u039b\u0397\u03a3\u0397", "recommended_consumables": "\u0391\u03bd\u03b1\u03bb\u03ce\u03c3\u03b9\u03bc\u03b1", "native_\ufeffar": "\u0627\u0644\u0639\u0631\u0628\u064a\u0629", "NextRank_": "\u0395\u03c0\u03cc\u03bc\u03b5\u03bd\u03b7 \u03b2\u03b1\u03b8\u03bc\u03af\u03b4\u03b1:", "neutralMinionsKilledTeamJungle": "\u0395\u03ba\u03c4\u03b5\u03bb\u03ad\u03c3\u03b5\u03b9\u03c2 \u03bf\u03c5\u03b4\u03ad\u03c4\u03b5\u03c1\u03c9\u03bd \u03c5\u03c0\u03b7\u03c1\u03b5\u03c4\u03ce\u03bd \u03c3\u03c4\u03b7 \u03b6\u03bf\u03cd\u03b3\u03ba\u03bb\u03b1 \u03c4\u03b7\u03c2 \u03bf\u03bc\u03ac\u03b4\u03b1\u03c2", "native_ja": "\u65e5\u672c\u8a9e", "Active": "\u0395\u03bd\u03b5\u03c1\u03b3\u03cc", "mode6v6": "FRONTEND_6v6_game_mode_name", "spells_target_100": "\u039a\u03b1\u03b8\u03bf\u03bb\u03b9\u03ba\u03cc", "magicalDamageTaken": "\u039c\u03b1\u03b3\u03b9\u03ba\u03ae \u03b6\u03b7\u03bc\u03b9\u03ac \u03b1\u03c0\u03cc \u03b5\u03c7\u03b8\u03c1\u03bf\u03cd\u03c2", "colloq_Consumables": ";", "Consumable": "\u0391\u03bd\u03b1\u03bb\u03ce\u03c3\u03b9\u03bc\u03b1", "ArmorPenetration": "\u0394\u03b9\u03b5\u03af\u03c3\u03b4\u03c5\u03c3\u03b7 \u0398\u03c9\u03c1\u03ac\u03ba\u03b9\u03c3\u03b7\u03c2", "AllItems": "\u038c\u03bb\u03b1 \u03c4\u03b1 \u03b1\u03bd\u03c4\u03b9\u03ba\u03b5\u03af\u03bc\u03b5\u03bd\u03b1", "rFlatHPRegenModPerLevel": "\u0391\u03bd\u03b1\u03c0\u03bb\u03ae\u03c1\u03c9\u03c3\u03b7 \u0396\u03c9\u03ae\u03c2 / 5 \u03c3\u03c4\u03bf \u03b5\u03c0. 18", "Slow": "\u0395\u03c0\u03b9\u03b2\u03c1\u03ac\u03b4\u03c5\u03bd\u03c3\u03b7", "Movement": "\u039a\u03af\u03bd\u03b7\u03c3\u03b7", "colloq_SpellBlock": ";mr", "mobileCompanion": "\u0392\u03bf\u03b7\u03b8\u03cc\u03c2", "colloq_CriticalStrike": ";", "colloq_SpellDamage": ";ap", "rFlatPhysicalDamageModPerLevel": "\u03a3\u03c9\u03bc\u03b1\u03c4\u03b9\u03ba\u03ae \u0396\u03b7\u03bc\u03b9\u03ac \u03c3\u03c4\u03bf \u03b5\u03c0. 18", "PlayingAs": "\u03a0\u03b1\u03af\u03b6\u03b5\u03b9 \u03c9\u03c2", "FlatHPPoolMod": "\u0396\u03c9\u03ae", "colloq_GoldPer": ";gp10;\u03c7\u03c110;gold;\u03c7\u03c1\u03c5\u03c3\u03bf\u03c2;\u03c7\u03c1\u03c5\u03c3\u03cc\u03c2", "Tips": "\u03a3\u03c5\u03bc\u03b2\u03bf\u03c5\u03bb\u03ad\u03c2", "OriginalCost_": "\u0391\u03c1\u03c7\u03b9\u03ba\u03cc \u03ba\u03cc\u03c3\u03c4\u03bf\u03c2:", "PercentMagicDamageMod": "% \u03bc\u03ad\u03b3\u03b9\u03c3\u03c4\u03b7\u03c2 \u0399\u03c3\u03c7\u03cd\u03bf\u03c2 \u0399\u03ba\u03b1\u03bd\u03cc\u03c4\u03b7\u03c4\u03b1\u03c2", "trueDamageDealtToChampions": "\u03a0\u03c1\u03b1\u03b3\u03bc\u03b1\u03c4\u03b9\u03ba\u03ae \u03b6\u03b7\u03bc\u03b9\u03ac \u03c3\u03b5 \u03ae\u03c1\u03c9\u03b5\u03c2", "native_bg": "\u0431\u044a\u043b\u0433\u0430\u0440\u0441\u043a\u0438 \u0435\u0437\u0438\u043a", "Stats": "\u03a3\u03c4\u03b1\u03c4\u03b9\u03c3\u03c4\u03b9\u03ba\u03ac", "SellsFor_": "\u03a4\u03b9\u03bc\u03ae \u03c0\u03ce\u03bb\u03b7\u03c3\u03b7\u03c2: ", "statDifficulty": "\u0394\u03c5\u03c3\u03ba\u03bf\u03bb\u03af\u03b1", "colloq_LifeSteal": ";lifesteal", "native_pt": "portugu\u00eas", "PercentAttackSpeedMod": "% T\u03b1\u03c7\u03cd\u03c4\u03b7\u03c4\u03b1 E\u03c0\u03af\u03b8\u03b5\u03c3\u03b7\u03c2", "colloq_Mana": ";mp;\u0394\u039c;\u03bc\u03b1\u03bd\u03b1;\u03bc\u03ac\u03bd\u03b1", "modeAram": "ARAM", "categorySummoner": "\u039e\u03cc\u03c1\u03ba\u03b9\u03b1 \u03b5\u03c0\u03b9\u03ba\u03b1\u03bb\u03b5\u03c3\u03c4\u03ae", "HealthRegen": "\u0391\u03bd\u03b1\u03c0\u03bb\u03ae\u03c1\u03c9\u03c3\u03b7 \u0396\u03c9\u03ae\u03c2", "native_ru": "\u0440\u0443\u0441\u0441\u043a\u0438\u0439 \u044f\u0437\u044b\u043a", "SpecialRecipeLarge": "\u0395\u03b9\u03b4\u03b9\u03ba\u03cc", "UpgradeCost_": "\u039a\u03cc\u03c3\u03c4\u03bf\u03c2 \u03b1\u03bd\u03b1\u03b2\u03ac\u03b8\u03bc\u03b9\u03c3\u03b7\u03c2:", "rFlatSpellBlockModPerLevel": "\u0391\u03bd\u03c4\u03af\u03c3\u03c4\u03b1\u03c3\u03b7 \u039c\u03b1\u03b3\u03b5\u03af\u03b1\u03c2 \u03c3\u03c4\u03bf \u03b5\u03c0. 18", "rFlatArmorModPerLevel": "\u0398\u03c9\u03c1\u03ac\u03ba\u03b9\u03c3\u03b7 \u03c3\u03c4\u03bf \u03b5\u03c0. 18", "ItemInfo": "\u03a0\u03bb\u03b7\u03c1\u03bf\u03c6\u03bf\u03c1\u03af\u03b5\u03c2 \u03b1\u03bd\u03c4\u03b9\u03ba\u03b5\u03b9\u03bc\u03ad\u03bd\u03bf\u03c5", "recommended_starting": "\u0391\u03c1\u03c7\u03b9\u03ba\u03ac \u0391\u03bd\u03c4\u03b9\u03ba\u03b5\u03af\u03bc\u03b5\u03bd\u03b1", "ChampionInfo": "\u03a0\u03bb\u03b7\u03c1\u03bf\u03c6\u03bf\u03c1\u03af\u03b5\u03c2 \u03b7\u03c1\u03ce\u03c9\u03bd", "spells_target_4": "\u03a0\u03b5\u03c1\u03b9\u03bf\u03c7\u03ae \u03bc\u03bf\u03bd\u03ac\u03b4\u03b1\u03c2", "mobileFriends": "\u03a6\u03af\u03bb\u03bf\u03b9", "categoryItem": "\u0391\u03bd\u03c4\u03b9\u03ba\u03b5\u03af\u03bc\u03b5\u03bd\u03b1", "colloq_Magic": ";", "Map1": "\u03a6\u03b1\u03c1\u03ac\u03b3\u03b3\u03b9 \u03c4\u03c9\u03bd \u0395\u03c0\u03b9\u03ba\u03b1\u03bb\u03b5\u03c3\u03c4\u03ce\u03bd", "rFlatMagicDamageModPerLevel": "\u0399\u03c3\u03c7\u03cd\u03c2 \u0399\u03ba\u03b1\u03bd\u03cc\u03c4\u03b7\u03c4\u03b1\u03c2 \u03c3\u03c4\u03bf \u03b5\u03c0. 18", "trueDamageDealt": "\u03a0\u03c1\u03b1\u03b3\u03bc\u03b1\u03c4\u03b9\u03ba\u03ae \u03b6\u03b7\u03bc\u03b9\u03ac \u03c3\u03b5 \u03b1\u03bd\u03c4\u03b9\u03c0\u03ac\u03bb\u03bf\u03c5\u03c2", "spells_target_1": "\u03a3\u03c4\u03cc\u03c7\u03bf\u03c2", "physicalDamageTaken": "\u03a3\u03c9\u03bc\u03b1\u03c4\u03b9\u03ba\u03ae \u03b6\u03b7\u03bc\u03b9\u03ac \u03b1\u03c0\u03cc \u03b5\u03c7\u03b8\u03c1\u03bf\u03cd\u03c2", "FlatEnergyPoolMod": "\u0395\u03bd\u03ad\u03c1\u03b3\u03b5\u03b9\u03b1", "goldEarned": "\u03a7\u03c1\u03c5\u03c3\u03cc\u03c2 \u03c0\u03bf\u03c5 \u03b1\u03c0\u03bf\u03ba\u03c4\u03ae\u03b8\u03b7\u03ba\u03b5", "Damage": "\u0396\u03b7\u03bc\u03b9\u03ac", "wards": "\u039c\u03ac\u03c4\u03b9\u03b1", "statAttack": "\u0395\u03c0\u03af\u03b8\u03b5\u03c3\u03b7", "statDefense": "\u0386\u03bc\u03c5\u03bd\u03b1", "Range": "\u0395\u03bc\u03b2\u03ad\u03bb\u03b5\u03b9\u03b1", "rFlatEnergyRegenModPerLevel": "\u0391\u03bd\u03b1\u03c0\u03bb\u03ae\u03c1\u03c9\u03c3\u03b7 \u0395\u03bd\u03ad\u03c1\u03b3\u03b5\u03b9\u03b1\u03c2 / 5 \u03c3\u03c4\u03bf \u03b5\u03c0. 18", "LifeSteal": "\u0391\u03c1\u03c0\u03b1\u03b3\u03ae \u0396\u03c9\u03ae\u03c2", "rFlatMovementSpeedModPerLevel": "\u03a4\u03b1\u03c7\u03cd\u03c4\u03b7\u03c4\u03b1 \u039a\u03af\u03bd\u03b7\u03c3\u03b7\u03c2 \u03c3\u03c4\u03bf \u03b5\u03c0. 18", "PercentHPPoolMod": "% \u03bc\u03ad\u03b3\u03b9\u03c3\u03c4\u03b7\u03c2 \u0396\u03c9\u03ae\u03c2", "goldSpent": "\u03a7\u03c1\u03c5\u03c3\u03cc\u03c2 \u03c0\u03bf\u03c5 \u03be\u03bf\u03b4\u03b5\u03cd\u03c4\u03b7\u03ba\u03b5", "masteryFerocity": "\u0391\u03b3\u03c1\u03b9\u03cc\u03c4\u03b7\u03c4\u03b1", "native_id": "Bahasa Indonesia", "Require_": "\u0391\u03c0\u03b1\u03b9\u03c4\u03b5\u03af:", "Gold": "\u03a7\u03c1\u03c5\u03c3\u03cc\u03c2", "spells_target_8": "\u039a\u03b1\u03c4\u03b5\u03cd\u03b8\u03c5\u03bd\u03c3\u03b7 \u03b5\u03c5\u03b8\u03b5\u03af\u03b1\u03c2 \u03b2\u03bf\u03bb\u03ae\u03c2", "masteryCunning": "\u03a0\u03b1\u03bd\u03bf\u03c5\u03c1\u03b3\u03af\u03b1", "FlatEXPBonus": "\u039c\u03c0\u03cc\u03bd\u03bf\u03c5\u03c2 \u03b5\u03bc\u03c0\u03b5\u03b9\u03c1\u03af\u03b1\u03c2", "FlatSpellBlockMod": "\u0391\u03bd\u03c4\u03af\u03c3\u03c4\u03b1\u03c3\u03b7 \u039c\u03b1\u03b3\u03b5\u03af\u03b1\u03c2", "PercentPhysicalDamageMod": "% \u03c3\u03c9\u03bc\u03b1\u03c4\u03b9\u03ba\u03ae\u03c2 \u03b6\u03b7\u03bc\u03b9\u03ac\u03c2", "rPercentMovementSpeedModPerLevel": "% \u03a4\u03b1\u03c7\u03cd\u03c4\u03b7\u03c4\u03b1 \u039a\u03af\u03bd\u03b7\u03c3\u03b7\u03c2 \u03c3\u03c4\u03bf \u03b5\u03c0. 18", "Range_": "\u0395\u03bc\u03b2\u03ad\u03bb\u03b5\u03b9\u03b1:", "sightWardsBoughtInGame": "\u0391\u03cc\u03c1\u03b1\u03c4\u03b1 \u039c\u03ac\u03c4\u03b9\u03b1 \u03c0\u03bf\u03c5 \u03b1\u03b3\u03bf\u03c1\u03ac\u03c3\u03c4\u03b7\u03ba\u03b1\u03bd", "FlatMovementSpeedMod": "\u03a4\u03b1\u03c7\u03cd\u03c4\u03b7\u03c4\u03b1 \u039a\u03af\u03bd\u03b7\u03c3\u03b7\u03c2", "SpellDamage": "\u0399\u03c3\u03c7\u03cd\u03c2 \u0399\u03ba\u03b1\u03bd\u03cc\u03c4\u03b7\u03c4\u03b1\u03c2", "modeTutorial": "\u039f\u03b4\u03b7\u03b3\u03cc\u03c2 \u03b5\u03ba\u03bc\u03ac\u03b8\u03b7\u03c3\u03b7\u03c2", "colloq_Defense": ";", "colloq_Health": ";hp;\u0396\u03c9\u03ae;\u03b6\u03c9\u03b7", "native_ko": "\uc870\uc120\ub9d0", "modeOneforall": "FRONTEND_oneforall_game_mode_name", "spells_target_5": "\u039c\u03b5\u03c4\u03b1\u03b2\u03bb\u03b7\u03c4\u03ae", "Support": "\u03a5\u03c0\u03bf\u03c3\u03c4\u03b7\u03c1\u03b9\u03ba\u03c4\u03ae\u03c2", "native_cs": "\u010de\u0161tina", "PercentCritChanceMod": "% \u03c0\u03b9\u03b8\u03b1\u03bd\u03cc\u03c4\u03b7\u03c4\u03b1\u03c2 \u039a\u03b1\u03af\u03c1\u03b9\u03bf\u03c5 \u03a7\u03c4.", "colloq_HealthRegen": ";hpregen;hp5;\u03b1\u03bd\u03b1\u03c0\u03bb. \u0396\u03c9\u03ae\u03c2;\u0396\u03c9\u03ae \u03b1\u03bd\u03ac 5", "FlatEnergyRegenMod": "\u0391\u03bd\u03b1\u03c0\u03bb\u03ae\u03c1\u03c9\u03c3\u03b7 \u0395\u03bd\u03ad\u03c1\u03b3\u03b5\u03b9\u03b1\u03c2 / 5", "statUtility": "\u03a5\u03c0\u03bf\u03c3\u03c4\u03ae\u03c1\u03b9\u03be\u03b7", "colloq_Damage": ";ad;\u0396\u0395", "rFlatMPRegenModPerLevel": "\u0391\u03bd\u03b1\u03c0\u03bb\u03ae\u03c1\u03c9\u03c3\u03b7 \u039c\u03ac\u03bd\u03b1 / 5 \u03c3\u03c4\u03bf \u03b5\u03c0. 18", "totalDamageDealt": "\u0396\u03b7\u03bc\u03b9\u03ac \u03c0\u03bf\u03c5 \u03ad\u03c7\u03b5\u03b9 \u03c0\u03c1\u03bf\u03ba\u03bb\u03b7\u03b8\u03b5\u03af", "ManaRegen": "\u0391\u03bd\u03b1\u03c0\u03bb\u03ae\u03c1\u03c9\u03c3\u03b7 \u039c\u03ac\u03bd\u03b1", "native_vn": "Ti\u1ebfng Vi\u1ec7t", "Map8": "\u0397 \u039a\u03c1\u03c5\u03c3\u03c4\u03ac\u03bb\u03bb\u03b9\u03bd\u03b7 \u039f\u03c5\u03bb\u03ae", "PercentMPRegenMod": "% \u039c\u03ac\u03bd\u03b1 / 5", "colloq_Attack": ";", "native_es": "espa\u00f1ol", "PercentLifeStealMod": "\u0391\u03c1\u03c0\u03b1\u03b3\u03ae \u0396\u03c9\u03ae\u03c2 %", "Level": "\u0395\u03c0\u03af\u03c0\u03b5\u03b4\u03bf", "colloq_MagicPenetration": ";", "masteryResolve": "\u0398\u03ad\u03bb\u03b7\u03c3\u03b7", "Builds_": "\u03a7\u03c4\u03af\u03b6\u03b5\u03b9:", "FlatCritDamageMod": "\u0396\u03b7\u03bc\u03b9\u03ac \u039a\u03b1\u03af\u03c1\u03b9\u03bf\u03c5 \u03a7\u03c4.", "FlatMagicDamageMod": "\u0399\u03c3\u03c7\u03cd\u03c2 \u0399\u03ba\u03b1\u03bd\u03cc\u03c4\u03b7\u03c4\u03b1\u03c2", "largestKillingSpree": "\u039c\u03b5\u03b3\u03b1\u03bb\u03cd\u03c4\u03b5\u03c1\u03b7 \u03c3\u03b5\u03b9\u03c1\u03ac \u03b5\u03ba\u03c4\u03b5\u03bb\u03ad\u03c3\u03b5\u03c9\u03bd", "physicalDamageDealt": "\u03a3\u03c9\u03bc\u03b1\u03c4\u03b9\u03ba\u03ae \u03b6\u03b7\u03bc\u03b9\u03ac \u03c3\u03b5 \u03b5\u03c7\u03b8\u03c1\u03bf\u03cd\u03c2", "PercentSpellVampMod": "\u039c\u03c0\u03cc\u03bd\u03bf\u03c5\u03c2 \u039c\u03b1\u03b3\u03b9\u03ba\u03ae \u0391\u03c1\u03c0\u03b1\u03b3\u03ae \u0396\u03c9\u03ae\u03c2 %", "FlatArmorMod": "\u0398\u03c9\u03c1\u03ac\u03ba\u03b9\u03c3\u03b7", "spells_Self": "\u039c\u03bf\u03bd\u03ac\u03b4\u03b1", "native_zh_CN": "\u7b80\u4f53\u5b57", "FlatBlockMod": "\u039c\u03c0\u03bb\u03bf\u03ba\u03ac\u03c1\u03b9\u03c3\u03bc\u03b1", "Defense": "\u0386\u03bc\u03c5\u03bd\u03b1", "rPercentAttackSpeedModPerLevel": "% \u03a4\u03b1\u03c7\u03cd\u03c4\u03b7\u03c4\u03b1 \u0395\u03c0\u03af\u03b8\u03b5\u03c3\u03b7\u03c2 \u03c3\u03c4\u03bf \u03b5\u03c0. 18", "native_en": "English", "CriticalStrike": "\u039a\u03b1\u03af\u03c1\u03b9\u03bf \u03c7\u03c4\u03cd\u03c0\u03b7\u03bc\u03b1", "Fighter": "\u039c\u03b1\u03c7\u03b7\u03c4\u03ae\u03c2", "PercentArmorMod": "% \u0398\u03c9\u03c1\u03ac\u03ba\u03b9\u03c3\u03b7\u03c2", "rFlatDodgeMod": "\u0391\u03c0\u03bf\u03c6\u03c5\u03b3\u03ae", "rFlatMagicPenetrationMod": "\u0394\u03b9\u03b5\u03af\u03c3\u03b4\u03c5\u03c3\u03b7 \u039c\u03b1\u03b3\u03b5\u03af\u03b1\u03c2", "categoryChampion": "\u0389\u03c1\u03c9\u03b5\u03c2", "rFlatCritChanceModPerLevel": "\u03a0\u03b9\u03b8\u03b1\u03bd\u03cc\u03c4\u03b7\u03c4\u03b1 \u039a\u03b1\u03af\u03c1\u03b9\u03bf\u03c5 \u03a7\u03c4. \u03c3\u03c4\u03bf \u03b5\u03c0. 18", "largestMultiKill": "\u039c\u03b5\u03b3\u03b1\u03bb\u03cd\u03c4\u03b5\u03c1\u03b7 \u03c0\u03bf\u03bb\u03bb\u03b1\u03c0\u03bb\u03ae \u03b5\u03ba\u03c4\u03ad\u03bb\u03b5\u03c3\u03b7", "visionWardsBoughtInGame": "\u0391\u03cc\u03c1\u03b1\u03c4\u03b1 \u039c\u03ac\u03c4\u03b9\u03b1 \u03c0\u03bf\u03c5 \u03b1\u03b3\u03bf\u03c1\u03ac\u03c3\u03c4\u03b7\u03ba\u03b1\u03bd", "totalHeal": "\u0396\u03b7\u03bc\u03b9\u03ac \u03c0\u03bf\u03c5 \u03b8\u03b5\u03c1\u03b1\u03c0\u03b5\u03cd\u03c4\u03b7\u03ba\u03b5", "RecommendedItems": "\u03a0\u03c1\u03bf\u03c4\u03b5\u03b9\u03bd\u03cc\u03bc\u03b5\u03bd\u03b1 \u03b1\u03bd\u03c4\u03b9\u03ba\u03b5\u03af\u03bc\u03b5\u03bd\u03b1", "PrimaryRole": "\u039a\u03cd\u03c1\u03b9\u03bf\u03c2 \u03c1\u03cc\u03bb\u03bf\u03c2", "statAbility": "\u0399\u03ba\u03b1\u03bd\u03cc\u03c4\u03b7\u03c4\u03b1", "PercentMPPoolMod": "% \u03bc\u03ad\u03b3\u03b9\u03c3\u03c4\u03bf\u03c5 \u039c\u03ac\u03bd\u03b1", "PercentMovementSpeedMod": "% \u03c4\u03b1\u03c7\u03cd\u03c4\u03b7\u03c4\u03b1\u03c2 \u03ba\u03af\u03bd\u03b7\u03c3\u03b7\u03c2", "rFlatArmorPenetrationMod": "\u0394\u03b9\u03b5\u03af\u03c3\u03b4\u03c5\u03c3\u03b7 \u0398\u03c9\u03c1\u03ac\u03ba\u03b9\u03c3\u03b7\u03c2", "rFlatArmorPenetrationModPerLevel": "\u0394\u03b9\u03b5\u03af\u03c3\u03b4\u03c5\u03c3\u03b7 \u0398\u03c9\u03c1\u03ac\u03ba\u03b9\u03c3\u03b7\u03c2 \u03c3\u03c4\u03bf \u03b5\u03c0. 18", "rFlatTimeDeadModPerLevel": "\u0394\u03b9\u03ac\u03c1\u03ba\u03b5\u03b9\u03b1 \u0398\u03b1\u03bd\u03ac\u03c4\u03bf\u03c5 \u03c3\u03c4\u03bf \u03b5\u03c0. 18", "PercentSpellBlockMod": "% \u0391\u03bd\u03c4\u03af\u03c3\u03c4\u03b1\u03c3\u03b7\u03c2 \u039c\u03b1\u03b3\u03b5\u03af\u03b1\u03c2", "Health": "\u0396\u03c9\u03ae", "colloq_CooldownReduction": ";cdr", "damageTakenHealed": "\u0396\u03b7\u03bc\u03b9\u03ac \u03b1\u03c0\u03cc \u03b5\u03c7\u03b8\u03c1\u03bf\u03cd\u03c2 \u03ba\u03b1\u03b9 \u03b6\u03b7\u03bc\u03b9\u03ac \u03c0\u03bf\u03c5 \u03b8\u03b5\u03c1\u03b1\u03c0\u03b5\u03cd\u03c4\u03b7\u03ba\u03b5", "wardsKilled": "\u039c\u03ac\u03c4\u03b9\u03b1 \u03c0\u03bf\u03c5 \u03ba\u03b1\u03c4\u03b1\u03c3\u03c4\u03c1\u03ac\u03c6\u03b7\u03ba\u03b1\u03bd", "PercentCritDamageMod": "% \u03b6\u03b7\u03bc\u03b9\u03ac\u03c2 \u039a\u03b1\u03af\u03c1\u03b9\u03bf\u03c5 \u03a7\u03c4.", "AttackSpeed": "\u03a4\u03b1\u03c7\u03cd\u03c4\u03b7\u03c4\u03b1 \u0395\u03c0\u03af\u03b8\u03b5\u03c3\u03b7\u03c2", "colloq_Armor": ";armour", "rPercentCooldownMod": "% \u03a7\u03c1\u03cc\u03bd\u03bf\u03c2 \u0395\u03c0\u03b1\u03bd\u03b1\u03c6\u03cc\u03c1\u03c4\u03b9\u03c3\u03b7\u03c2", "colloq_Aura": ";", "Back": "\u0395\u03c0\u03b9\u03c3\u03c4\u03c1\u03bf\u03c6\u03ae", "PlayingAgainst": "\u0391\u03bd\u03c4\u03af\u03c0\u03b1\u03bb\u03bf\u03b9", "native_zh_MY": "\u7b80\u4f53\u5b57", "neutralMinionsKilled": "\u0395\u03ba\u03c4\u03b5\u03bb\u03ad\u03c3\u03b5\u03b9\u03c2 \u03bf\u03c5\u03b4\u03ad\u03c4\u03b5\u03c1\u03c9\u03bd \u03c4\u03b5\u03c1\u03ac\u03c4\u03c9\u03bd", "spells_target_6": "\u0398\u03ad\u03c3\u03b7", "GoldPer": "\u0395\u03b9\u03c3\u03cc\u03b4\u03b7\u03bc\u03b1 \u03c7\u03c1\u03c5\u03c3\u03bf\u03cd", "FlatAttackSpeedMod": "\u03a4\u03b1\u03c7\u03cd\u03c4\u03b7\u03c4\u03b1 \u0395\u03c0\u03af\u03b8\u03b5\u03c3\u03b7\u03c2", "KDA": "\u0395\u0398\u0392", "spells_target_7": "\u039a\u03b1\u03c4\u03b5\u03cd\u03b8\u03c5\u03bd\u03c3\u03b7", "recommended_defensive": "\u0391\u03bc\u03c5\u03bd\u03c4\u03b9\u03ba\u03ac \u03b1\u03bd\u03c4\u03b9\u03ba\u03b5\u03af\u03bc\u03b5\u03bd\u03b1", "Magic": "\u039c\u03b1\u03b3\u03b5\u03af\u03b1", "categoryRune": "\u03a1\u03bf\u03cd\u03bd\u03bf\u03b9", "PercentHPRegenMod": "% \u0396\u03c9\u03ae\u03c2 / 5", "native_zh_TW": "\u7e41\u9ad4\u5b57", "mobileForum": "\u03a6\u03cc\u03c1\u03bf\u03c5\u03bc", "rPercentArmorPenetrationMod": "\u0394\u03b9\u03b5\u03af\u03c3\u03b4\u03c5\u03c3\u03b7 \u0398\u03c9\u03c1\u03ac\u03ba\u03b9\u03c3\u03b7\u03c2 %", "native_zh": "\u6c49\u8bed", "SpecialRecipeSmall": "*"}