{"native_th": "\u0e20\u0e32\u0e29\u0e32\u0e44\u0e17\u0e22", "PercentDodgeMod": "% uniku", "positionJungle": "D\u017cungla", "Continue": "Kontynuuj", "outcomeDefeat": "Pora\u017cka", "native_it": "Italiano", "FlatMPRegenMod": "Regeneracja many / 5", "mobileNews": "Wiadomo\u015bci", "favorites": "Ulubieni", "mobilePleaseWait": "Prosz\u0119 czeka\u0107...", "Aura": "Aura", "positionMiddle": "\u015arodek", "Cost_": "Cena:", "PercentEXPBonus": "% dodatkowych PD", "CooldownReduction": "Czas odnowienia", "rPercentMagicPenetrationMod": "Przebicie odporno\u015bci %", "ButtonBuy": "KUP", "colloq_Movement": ";movespeed", "physicalDamageDealtToChampions": "Obra\u017cenia fizyczne zadawane bohaterom", "maximumAbbreviation": "maks", "wardsPlaced": "Rozstawione totemy", "Language": "J\u0119zyk", "rFlatMPModPerLevel": "Mana na 18. poziomie", "Attack": "Atak", "Mana": "Mana", "charts": "Analiza", "colloq_NonbootsMovement": ";", "rPercentCooldownModPerLevel": "% czasu odnowienia na 18. poziomie", "colloq_ManaRegen": ";pmregen;pm5", "Lore": "Historia", "native_fr": "fran\u00e7ais", "colloq_Active": ";", "rFlatHPModPerLevel": "Zdrowie na 18. poziomie", "damageDealt": "Zadane obra\u017cenia", "recentSearches": "Ostatnie wyszukiwania", "modeFirstblood": "FRONTEND_firstblood_game_mode_name", "Boots": "Buty", "native_nl": "Nederlands", "magicDamageDealt": "Zadane obra\u017cenia magiczne", "recommended_essential": "Niezb\u0119dne przedmioty", "colloq_Consumable": ";", "itemBuyOrder": "Wed\u0142ug kupionych przedmiot\u00f3w", "Rank_": "Ranga:", "modeClassic": "Klasyczna", "participants": "Uczestnicy", "noMatchesFoundWithUsedCriterias": "Nie znaleziono pasuj\u0105cych meczu!", "FlatHPRegenMod": "Regeneracja zdrowia / 5", "native_de": "Deutsch", "noChampionFoundUrl": "Nie znaleziono bohatera w podanym URL!", "totalMinionsKilled": "Zabite stwory", "Tank": "Obro\u0144ca", "PercentBlockMod": "% bloku", "played": "Rozegrano", "native_hu": "magyar", "native_el": "\u03b5\u03bb\u03bb\u03b7\u03bd\u03b9\u03ba\u03ac", "rFlatCritDamageModPerLevel": "Obra\u017cenia od trafienia krytycznego na 18. poziomie", "neutralMinionsKilledTeamJungle": "Neutralne stwory zabite we w\u0142asnej d\u017cungli", "firstBloodKill": "Pierwsza krew", "noChampionFoundWithUsedCriterias": "Nie znaleziono pasuj\u0105cych bohater\u00f3w!", "Mage": "Mag", "breakdown": "Prze\u0142amania", "modeOdin": "Na Pewno Nie Dominion", "rPercentMagicPenetrationModPerLevel": "Przebicie odporno\u015bci % na 18. poziomie", "colloq_Slow": ";", "colloq_SpellVamp": ";wampiryzm zakl\u0119\u0107", "Abilities": "Umiej\u0119tno\u015bci", "native_pl": "j\u0119zyk polski", "rFlatMagicPenetrationModPerLevel": "Przebicie odporno\u015bci na 18. poziomie", "Marksman": "Strzelec", "Assassin": "Zab\u00f3jca", "rPercentTimeDeadMod": "% czasu bycia martwym", "rFlatDodgeModPerLevel": "Unik na 18. poziomie", "rPercentArmorPenetrationModPerLevel": "Przebicie pancerza % na 18. poziomie", "combat": "Walka", "CD_": "CO:", "rFlatTimeDeadMod": "Czas bycia martwym", "message": "Wiadomo\u015b\u0107", "Details_": "Szczeg\u00f3\u0142y:", "mailSentHeader": "Wiadomo\u015b\u0107 wys\u0142ana pomy\u015blnie", "positionAdCarry": "Strzelec", "colloq_AttackSpeed": ";as", "spells_target_2": "Obszar", "colloq_ArmorPenetration": ";", "overview": "Podsumowanie", "trueDamageTaken": "Otrzymane nieuchronne obra\u017cenia", "income": "Przych\u00f3d", "recentMatches": "Ostatnie mecze", "magicDamageDealtToChampions": "Obra\u017cenia magiczne zadawane bohaterom", "modeCof": "FRONTEND_cof_game_mode_name", "MagicPenetration": "Przebicie odporno\u015bci", "tryUseOtherCriterias": "Spr\u00f3buj u\u017cy\u0107 innych kryteri\u00f3w", "sightWardsBoughtInGame": "Kupione Totemy Ukrycia", "recommended_offensive": "Przedmioty ofensywne", "SpellVamp": "Wampiryzm zakl\u0119\u0107", "Tenacity": "Nieust\u0119pliwo\u015b\u0107", "SpellBlock": "Odporno\u015b\u0107 na magi\u0119", "FlatPhysicalDamageMod": "Obra\u017cenia", "rFlatEnergyModPerLevel": "Energia na 18. poziomie", "colloq_Tenacity": ";", "keystoneMastery": "Runa kluczowa", "NonbootsMovement": "Inne przedmioty ruchu", "mostPopularItems": "Najbardziej popularne przedmioty", "rPercentTimeDeadModPerLevel": "% czasu bycia martwym na poziom", "Armor": "Pancerz", "mailSentDescription": "Otrzymali\u015bmy Twoj\u0105 wiadomo\u015b\u0107 i postaramy si\u0119 odpowiedzie\u0107 w jak najszybszym tempie. Dzi\u0119kujemy za skontaktowanie si\u0119 z nami.", "noProFoundUrl": "Nie znaleziono profesjonalisty w podanym URL!", "native_tr": "T\u00fcrk\u00e7e", "FlatMPPoolMod": "Mana", "colloq_Boots": ";", "Map12": "Howling Abyss", "native_ro": "rom\u00e2n\u0103", "spells_target_3": "Sto\u017cek", "neutralMinionsKilledEnemyJungle": "Neutralne stwory zabite w d\u017cungli przeciwnik\u00f3w", "largestCriticalStrike": "Najwi\u0119ksze trafienie krytyczne", "spells_target_0": "W\u0142asne", "rFlatGoldPer10Mod": "Z\u0142oto /10", "FlatCritChanceMod": "Szansa na trafienie krytyczne", "Map10": "Twisted Treeline", "categoryMastery": "Specjalizacje", "ButtonSell": "SPRZEDAJ", "recommended_consumables": "Zaopatrzenie", "native_\ufeffar": "\u0627\u0644\u0639\u0631\u0628\u064a\u0629", "NextRank_": "Nast\u0119pny poziom:", "magicalDamageTaken": "Otrzymane obra\u017cenia magiczne", "native_ja": "\u65e5\u672c\u8a9e", "Active": "Aktywne", "mode6v6": "FRONTEND_6v6_game_mode_name", "showMoreDots": "Poka\u017c wi\u0119cej \u2026", "spells_target_100": "Globalny", "positionSupport": "Wsparcie", "colloq_Consumables": ";", "Consumable": "Zaopatrzenie", "spellSkillOrder": "Wed\u0142ug rozdanych umiej\u0119tno\u015bci", "ArmorPenetration": "Przebicie pancerza", "AllItems": "Wszystkie przedmioty", "rFlatHPRegenModPerLevel": "Regeneracja zdrowia / 5 na 18. poziomie", "about": "O nas", "Slow": "Spowolnienie", "Movement": "Ruch", "contact": "Kontakt", "colloq_SpellBlock": ";mr", "pros": "Profesjonali\u015bci", "mobileCompanion": "Towarzysz", "noProFoundWithUsedCriterias": "Nie znaleziono pasuj\u0105cych profesjonalist\u00f3w!", "colloq_CriticalStrike": ";", "colloq_SpellDamage": ";ap", "matchLength": "D\u0142ugo\u015b\u0107 meczu", "rFlatPhysicalDamageModPerLevel": "Obra\u017cenia na 18. poziomie", "PlayingAs": "Gra jako", "FlatHPPoolMod": "Zdrowie", "colloq_GoldPer": ";szn10", "loadingDots": "\u0141adowanie \u2026", "Tips": "Wskaz\u00f3wki", "OriginalCost_": "Podstawowa cena:", "PercentMagicDamageMod": "% maksymalnej mocy umiej\u0119tno\u015bci", "trueDamageDealtToChampions": "Nieuchronne obra\u017cenia zadane bohaterom", "native_bg": "\u0431\u044a\u043b\u0433\u0430\u0440\u0441\u043a\u0438 \u0435\u0437\u0438\u043a", "searchForPro": "Szukaj profesjonalisty", "Stats": "Statystyki", "name": "Imi\u0119", "SellsFor_": "Sprzeda\u017c za: ", "statDifficulty": "Trudno\u015b\u0107", "colloq_LifeSteal": ";kradzie\u017c \u017cycia", "native_pt": "portugu\u00eas", "PercentAttackSpeedMod": "% pr\u0119dko\u015bci ataku", "colloq_Mana": ";pm", "modeAram": "ARAM", "categorySummoner": "Czary przywo\u0142ywacza:", "champions": "Bohaterowie", "statistics": "Statystyki", "HealthRegen": "Regeneracja zdrowia", "native_ru": "\u0440\u0443\u0441\u0441\u043a\u0438\u0439 \u044f\u0437\u044b\u043a", "SpecialRecipeLarge": "Specjalne", "contactUsInCaseOfError": "Skontaktuj si\u0119 z nami w razie b\u0142\u0119du.", "UpgradeCost_": "Cena ulepszenia:", "starterItems": "Pocz\u0105tkowe przedmioty", "rFlatSpellBlockModPerLevel": "Odporno\u015b\u0107 na magi\u0119 na 18. poziomie", "rFlatArmorModPerLevel": "Pancerz na 18. poziomie", "finalItemBuild": "Uko\u0144czony build", "ItemInfo": "Informacje o przedmiocie", "patch": "Patch {patch}", "recommended_starting": "Przedmioty pocz\u0105tkowe", "ChampionInfo": "Informacje o bohaterze", "spells_target_4": "Obszar w\u0142asny", "mobileFriends": "Znajomi", "categoryItem": "Przedmioty", "colloq_Magic": ";", "Map1": "Summoner's Rift", "noMatchFoundUrl": "Nie znaeziono meczu w podanym URL!", "keystonePerks": "Runa wi\u0119ksza", "rFlatMagicDamageModPerLevel": "Moc umiej\u0119tno\u015bci na 18. poziomie", "trueDamageDealt": "Zadane nieuchronne obra\u017cenia", "spells_target_1": "Cel", "physicalDamageTaken": "Przyj\u0119te obra\u017cenia fizyczne", "FlatEnergyPoolMod": "Energia", "goldEarned": "Zdobyte z\u0142oto", "finalBoots": "Ko\u0144cowe buty", "Damage": "Obra\u017cenia", "wards": "Totemy", "statAttack": "Atak", "statDefense": "Obrona", "Range": "Zasi\u0119g", "rFlatEnergyRegenModPerLevel": "Regeneracja energii / 5 na 18. poziomie", "LifeSteal": "Kradzie\u017c \u017cycia", "rFlatMovementSpeedModPerLevel": "Pr\u0119dko\u015b\u0107 ruchu na 18. poziomie", "PercentHPPoolMod": "% maksymalnego zdrowia", "goldSpent": "Wydane z\u0142oto", "masteryFerocity": "Zaciek\u0142o\u015b\u0107", "native_id": "Bahasa Indonesia", "Require_": "Wymaga:", "Gold": "Z\u0142oto", "mailErrorHeader": "Wyst\u0105pi\u0142 b\u0142\u0105d", "spells_target_8": "Kierunek", "masteryCunning": "Przebieg\u0142o\u015b\u0107", "FlatEXPBonus": "Dodatkowe PD", "FlatSpellBlockMod": "Odporno\u015b\u0107 na magi\u0119", "PercentPhysicalDamageMod": "% obra\u017ce\u0144 fizycznych", "rPercentMovementSpeedModPerLevel": "% pr\u0119dko\u015bci ruchu na 18. poziomie", "legalDisclosure": "Ujawnenie prawne", "Range_": "Zasi\u0119g:", "totalDamageDealt": "Zadane obra\u017cenia", "FlatMovementSpeedMod": "Pr\u0119dko\u015b\u0107 ruchu", "SpellDamage": "Moc umiej\u0119tno\u015bci", "modeTutorial": "Samouczek", "colloq_Defense": ";", "colloq_Health": ";pz", "native_ko": "\uc870\uc120\ub9d0", "modeOneforall": "FRONTEND_oneforall_game_mode_name", "outcomeVictory": "Zwyci\u0119stwo", "spells_target_5": "Zmienna", "Support": "Wsparcie", "native_cs": "\u010de\u0161tina", "PercentCritChanceMod": "% na trafienie krytyczne", "colloq_HealthRegen": ";pzregen;pz5", "position": "Pozycja", "mailErrorDescription": "Prosimy rozwi\u0105\u017c CAPTCHA przed wys\u0142aniem zg\u0142oszenia.", "searchDots": "Szukanie \u2026", "FlatEnergyRegenMod": "Regeneracja energii / 5", "statUtility": "U\u017cytkowe", "colloq_Damage": ";ooa", "rFlatMPRegenModPerLevel": "Regeneracja many / 5 na 18. poziomie", "minutesAbbreviation": "min", "ManaRegen": "Regeneracja many", "native_vn": "Ti\u1ebfng Vi\u1ec7t", "summary": "Podsumowanie", "Map8": "The Crystal Scar", "free": "Darmowa", "PercentMPRegenMod": "% many / 5", "colloq_Attack": ";", "damageTakenHealed": "Obra\u017cenia otrzymane i wyleczone", "native_es": "espa\u00f1ol", "PercentLifeStealMod": "% bonus do kradzie\u017cy \u017cycia", "Level": "Poziom", "colloq_MagicPenetration": ";", "age": "Wiek {wiek}", "masteryResolve": "Determinacja", "positionTop": "G\u00f3ra", "Builds_": "Wchodzi w sk\u0142ad:", "FlatCritDamageMod": "Obra\u017cenia od trafienia krytycznego", "FlatMagicDamageMod": "Moc umiej\u0119tno\u015bci", "firstTowerDestroyed": "Pierwsza zniszczona wie\u017ca", "minmumAbbreviation": "min", "contactUs": "Skontaktuj si\u0119 z nami", "largestKillingSpree": "Najwi\u0119ksza seria zab\u00f3jstw", "physicalDamageDealt": "Zadane obra\u017cenia fizyczne", "PercentSpellVampMod": "% bonus wampiryzmu zakl\u0119\u0107", "FlatArmorMod": "Pancerz", "spells_Self": "W\u0142asne", "messageDescription": "Zostaw nam wiadomo\u015b\u0107 \u2026", "native_zh_CN": "\u7b80\u4f53\u5b57", "Map11": "Summoner's Rift", "FlatBlockMod": "Blok", "Defense": "Obrona", "rPercentAttackSpeedModPerLevel": "% pr\u0119dko\u015bci ataku na 18. poziomie", "privacyPolicy": "Polityka prywatno\u015bci", "opponent": "Przeciwnik", "killParticipation": "Udzia\u0142 w zab\u00f3jstwach", "native_en": "English", "CriticalStrike": "Trafienie krytyczne", "apart": "Osobno", "Fighter": "Wojownik", "PercentArmorMod": "% pancerza", "rFlatDodgeMod": "Unik", "scoreboard": "Wynik", "perfect": "Idealne", "rFlatMagicPenetrationMod": "Przebicie odporno\u015bci ", "subject": "Temat", "categoryChampion": "Bohaterowie", "rFlatCritChanceModPerLevel": "Szansa na trafienie krytyczne na 18. poziomie", "largestMultiKill": "Najwi\u0119ksze wielob\u00f3jstwo", "visionWardsBoughtInGame": "Kupione Totemy Wizji", "totalHeal": "Obra\u017cenia wyleczone", "RecommendedItems": "Polecane przedmioty", "PrimaryRole": "G\u0142\u00f3wna rola", "statAbility": "Umiej\u0119tno\u015bci", "PercentMPPoolMod": "% maksymalnej many", "PercentMovementSpeedMod": "% pr\u0119dko\u015bci ruchu", "outcomeRemake": "Remake", "totalDamageDealtToChampions": "Obra\u017cenia zadane bohaterom", "rank": "Ranga", "rFlatArmorPenetrationMod": "Przebicie pancerza", "rFlatArmorPenetrationModPerLevel": "Przebicie pancerza na 18. poziomie", "rFlatTimeDeadModPerLevel": "Czas bycia martwym na 18. poziomie", "PercentSpellBlockMod": "% odporno\u015bci na magi\u0119", "email": "Email", "Health": "Zdrowie", "colloq_CooldownReduction": ";cdr", "mostPopularSetup": "Najbardziej popularny uk\u0142ad", "wardsKilled": "Zniszczone totemy", "PercentCritDamageMod": "% obra\u017ce\u0144 od trafienia krytycznego", "AttackSpeed": "Pr\u0119dko\u015b\u0107 ataku", "playing": "W grze", "mostPopular": "Najbardziej popularne", "colloq_Armor": ";pancerz", "rPercentCooldownMod": "% czasu odnowienia", "colloq_Aura": ";", "searchForChampion": "Szukaj bohatera", "Back": "Cofnij", "submit": "Wy\u015blij", "PlayingAgainst": "Przeciwnik", "native_zh_MY": "\u7b80\u4f53\u5b57", "neutralMinionsKilled": "Zabite neutralne stwory", "totalDamageTaken": "Przyj\u0119te obra\u017cenia", "spells_target_6": "Miejsce", "GoldPer": "Przych\u00f3d z\u0142ota", "finalTrinket": "Ko\u0144cowy trinket", "FlatAttackSpeedMod": "Pr\u0119dko\u015b\u0107 ataku", "searchChampionsProsDots": "Szukaj bohater\u00f3w i profesjonalist\u00f3w", "KDA": "KDA", "won": "Wygrana", "spells_target_7": "Kierunek", "recommended_defensive": "Przedmioty defensywne", "Magic": "Magia", "categoryRune": "Runy", "PercentHPRegenMod": "% zdrowia / 5", "native_zh_TW": "\u7e41\u9ad4\u5b57", "mobileForum": "Forum", "rPercentArmorPenetrationMod": "Przebicie pancerza %", "native_zh": "\u6c49\u8bed", "SpecialRecipeSmall": "*"}